lab2/mux_41/mux_41.v
module mux_41(a,b,c,d,sel,f);
input a,b,c,d;
input [1:0]sel;
output reg f;
always@(a or b or c or d or sel)
case (sel)
    2'b00: f<=a;
    2'b01: f<=b;
    2'b10: f<=c;
    2'b11: f<=d;
endcase

endmodule

lab2/mux_41/mux_41_tb.v
`timescale 1ns / 1ps
`include "mux_41.v"
`timescale 1ns / 1ps

module mux_41_tb;

    // Testbench signals
    reg a;
    reg b;
    reg c;
    reg d;
    reg [1:0] sel;
    wire f;

    // Instantiate the mux_41 module
    mux_41 uut (
        .a(a),
        .b(b),
        .c(c),
        .d(d),
        .sel(sel),
        .f(f)
    );

    initial begin
        // Initialize signals
        a = 0;
        b = 0;
        c = 0;
        d = 0;
        sel = 2'b00;

        // Monitor outputs
        $monitor("At time %t: a = %b, b = %b, c = %b, d = %b, sel = %b -> f = %b", $time, a, b, c, d, sel, f);

        // Test all combinations of sel with different input values
        #10; a = 1; b = 0; c = 0; d = 0; sel = 2'b00;
        #10; a = 0; b = 1; c = 0; d = 0; sel = 2'b01;
        #10; a = 0; b = 0; c = 1; d = 0; sel = 2'b10;
        #10; a = 0; b = 0; c = 0; d = 1; sel = 2'b11;

        // Test with multiple inputs being high
        #10; a = 1; b = 1; c = 0; d = 0; sel = 2'b00;
        #10; a = 0; b = 1; c = 1; d = 0; sel = 2'b01;
        #10; a = 0; b = 0; c = 1; d = 1; sel = 2'b10;
        #10; a = 1; b = 0; c = 0; d = 1; sel = 2'b11;

        // Test with all inputs being high
        #10; a = 1; b = 1; c = 1; d = 1; sel = 2'b00;
        #10; sel = 2'b01;
        #10; sel = 2'b10;
        #10; sel = 2'b11;

        // Finish the simulation
        #10;
        $finish;
    end
 initial begin
        $dumpfile("mux_41_waveform.vcd");
        $dumpvars(0,mux_41_tb);
    end
endmodule

lab2/mux_41/mux_41_waveform.vcd
$date
	Tue Jul 23 10:48:57 2024
$end
$version
	Icarus Verilog
$end
$timescale
	1ps
$end
$scope module mux_41_tb $end
$var wire 1 ! f $end
$var reg 1 " a $end
$var reg 1 # b $end
$var reg 1 $ c $end
$var reg 1 % d $end
$var reg 2 & sel [1:0] $end
$scope module uut $end
$var wire 1 " a $end
$var wire 1 # b $end
$var wire 1 $ c $end
$var wire 1 % d $end
$var wire 2 ' sel [1:0] $end
$var reg 1 ! f $end
$upscope $end
$upscope $end
$enddefinitions $end
#0
$dumpvars
b0 '
b0 &
0%
0$
0#
0"
0!
$end
#10000
1!
1"
#20000
b1 &
b1 '
1#
0"
#30000
b10 &
b10 '
1$
0#
#40000
b11 &
b11 '
1%
0$
#50000
b0 &
b0 '
0%
1#
1"
#60000
b1 &
b1 '
1$
0"
#70000
b10 &
b10 '
1%
0#
#80000
b11 &
b11 '
0$
1"
#90000
b0 &
b0 '
1$
1#
#100000
b1 &
b1 '
#110000
b10 &
b10 '
#120000
b11 &
b11 '
