lab2/prencoder_83/prencoder_83.v
module prencoder_83(en,i,y);
    input en;
    input [7:0]i;
    output [2:0]y;

    assign y[2]=i[4] | i[5] | i[6] | i[7] &en;
    assign y[1]=i[2] | i[3] | i[6] | i[7] &en;
    assign y[0]=i[1] | i[3] | i[5] | i[7] &en;

endmodule

lab2/prencoder_83/prencoder_83_tb.v
`include "prencoder_83.v"
module prencoder_83_tb;
  reg [7:0]i;
  reg en;
  wire [2:0]y;
  
  prencoder_83 dut(en,i,y);
  initial
    begin
      $monitor("en=%b i=%b y=%b",en,i,y);
      en=1; i=128;#5
      en=1; i=64;#5
      en=1; i=32;#5
      en=1; i=16;#5
      en=1; i=8;#5
      en=1; i=4;#5
      en=1; i=2;#5
      en=1; i=0;#5
      en=0;i=8'bx;#5
      $finish;
    end
    
     initial begin
        $dumpfile("prencoder_83_waveform.vcd");
        $dumpvars(0,prencoder_83_tb);
    end
endmodule

lab2/prencoder_83/prencoder_83_waveform.vcd
$date
	Tue Jul 23 11:03:38 2024
$end
$version
	Icarus Verilog
$end
$timescale
	1s
$end
$scope module prencoder_83_tb $end
$var wire 3 ! y [2:0] $end
$var reg 1 " en $end
$var reg 8 # i [7:0] $end
$scope module dut $end
$var wire 1 " en $end
$var wire 8 $ i [7:0] $end
$var wire 3 % y [2:0] $end
$upscope $end
$upscope $end
$enddefinitions $end
#0
$dumpvars
b111 %
b10000000 $
b10000000 #
1"
b111 !
$end
#5
b110 !
b110 %
b1000000 #
b1000000 $
#10
b101 !
b101 %
b100000 #
b100000 $
#15
b100 !
b100 %
b10000 #
b10000 $
#20
b11 !
b11 %
b1000 #
b1000 $
#25
b10 !
b10 %
b100 #
b100 $
#30
b1 !
b1 %
b10 #
b10 $
#35
b0 !
b0 %
b0 #
b0 $
#40
bx !
bx %
bx #
bx $
0"
