lab1/mux_41_mux_21/mux_41_mux_21.v
module mux_21(x,y,s,f1);
input x,y,s;
output f1;
assign f1= s? x:y;
endmodule

module mux_41(a,b,c,d,s0,s1,f2);
input a,b,c,d,s0,s1;
output f2;
wire W1,W2;
mux_21 M1(a,b,s0,W1);
mux_21 M2(c,d,s0,W2);
mux_21 M3(W1,W2,s1,f2);
endmodule

lab1/mux_41_mux_21/mux_41_mux_21_tb.v
`timescale 1ns / 1ps
`include "mux_41_mux_21.v"
module mux_41_tb;

    // Testbench signals
    reg a;
    reg b;
    reg c;
    reg d;
    reg s0;
    reg s1;
    wire f2;

    // Instantiate the mux_41 module
    mux_41 uut (
        .a(a),
        .b(b),
        .c(c),
        .d(d),
        .s0(s0),
        .s1(s1),
        .f2(f2)
    );

    initial begin
        // Initialize signals
        a = 0;
        b = 0;
        c = 0;
        d = 0;
        s0 = 0;
        s1 = 0;

        // Monitor outputs
        $monitor("At time %t: a = %b, b = %b, c = %b, d = %b, s0 = %b, s1 = %b -> f2 = %b", $time, a, b, c, d, s0, s1, f2);

        // Test all combinations of inputs and select lines
        #10; {a, b, c, d, s0, s1} = 6'b000000;
        #10; {a, b, c, d, s0, s1} = 6'b000001;
        #10; {a, b, c, d, s0, s1} = 6'b000010;
        #10; {a, b, c, d, s0, s1} = 6'b000011;
        #10; {a, b, c, d, s0, s1} = 6'b001000;
        #10; {a, b, c, d, s0, s1} = 6'b001001;
        #10; {a, b, c, d, s0, s1} = 6'b001010;
        #10; {a, b, c, d, s0, s1} = 6'b001011;
        #10; {a, b, c, d, s0, s1} = 6'b010000;
        #10; {a, b, c, d, s0, s1} = 6'b010001;
        #10; {a, b, c, d, s0, s1} = 6'b010010;
        #10; {a, b, c, d, s0, s1} = 6'b010011;
        #10; {a, b, c, d, s0, s1} = 6'b011000;
        #10; {a, b, c, d, s0, s1} = 6'b011001;
        #10; {a, b, c, d, s0, s1} = 6'b011010;
        #10; {a, b, c, d, s0, s1} = 6'b011011;
        #10; {a, b, c, d, s0, s1} = 6'b100000;
        #10; {a, b, c, d, s0, s1} = 6'b100001;
        #10; {a, b, c, d, s0, s1} = 6'b100010;
        #10; {a, b, c, d, s0, s1} = 6'b100011;
        #10; {a, b, c, d, s0, s1} = 6'b101000;
        #10; {a, b, c, d, s0, s1} = 6'b101001;
        #10; {a, b, c, d, s0, s1} = 6'b101010;
        #10; {a, b, c, d, s0, s1} = 6'b101011;
        #10; {a, b, c, d, s0, s1} = 6'b110000;
        #10; {a, b, c, d, s0, s1} = 6'b110001;
        #10; {a, b, c, d, s0, s1} = 6'b110010;
        #10; {a, b, c, d, s0, s1} = 6'b110011;
        #10; {a, b, c, d, s0, s1} = 6'b111000;
        #10; {a, b, c, d, s0, s1} = 6'b111001;
        #10; {a, b, c, d, s0, s1} = 6'b111010;
        #10; {a, b, c, d, s0, s1} = 6'b111011;

        // Finish the simulation
        #10;
        $finish;
    end

 initial begin
        $dumpfile("mux_41_waveform.vcd");
        $dumpvars(0,mux_41_tb);
    end
endmodule

lab1/mux_41_mux_21/mux_41_waveform.vcd
$date
	Mon Jul 22 22:48:19 2024
$end
$version
	Icarus Verilog
$end
$timescale
	1ps
$end
$scope module mux_41_tb $end
$var wire 1 ! f2 $end
$var reg 1 " a $end
$var reg 1 # b $end
$var reg 1 $ c $end
$var reg 1 % d $end
$var reg 1 & s0 $end
$var reg 1 ' s1 $end
$scope module uut $end
$var wire 1 " a $end
$var wire 1 # b $end
$var wire 1 $ c $end
$var wire 1 % d $end
$var wire 1 & s0 $end
$var wire 1 ' s1 $end
$var wire 1 ! f2 $end
$var wire 1 ( W2 $end
$var wire 1 ) W1 $end
$scope module M1 $end
$var wire 1 & s $end
$var wire 1 " x $end
$var wire 1 # y $end
$var wire 1 ) f1 $end
$upscope $end
$scope module M2 $end
$var wire 1 & s $end
$var wire 1 $ x $end
$var wire 1 % y $end
$var wire 1 ( f1 $end
$upscope $end
$scope module M3 $end
$var wire 1 ' s $end
$var wire 1 ) x $end
$var wire 1 ( y $end
$var wire 1 ! f1 $end
$upscope $end
$upscope $end
$upscope $end
$enddefinitions $end
#0
$dumpvars
0)
0(
0'
0&
0%
0$
0#
0"
0!
$end
#20000
1'
#30000
1&
0'
#40000
1'
#50000
1$
0&
0'
#60000
1'
#70000
1!
1(
1&
0'
#80000
0!
1'
#90000
1)
0(
0!
1#
0$
0&
0'
#100000
1!
1'
#110000
0)
0!
1&
0'
#120000
1'
#130000
1)
1$
0&
0'
#140000
1!
1'
#150000
0)
1(
1!
1&
0'
#160000
0!
1'
#170000
0(
0!
1"
0#
0$
0&
0'
#180000
1'
#190000
1)
1&
0'
#200000
1!
1'
#210000
0)
0!
1$
0&
0'
#220000
1'
#230000
1!
1)
1(
1&
0'
#240000
1'
#250000
0!
0(
1#
0$
0&
0'
#260000
1!
1'
#270000
0!
1&
0'
#280000
1!
1'
#290000
0!
1$
0&
0'
#300000
1!
1'
#310000
1(
1!
1&
0'
#320000
1'
