lab1/decoder_24/decoder_24.v
module decoder_24(en,a,b,w,x,y,z);
input a,b,en;
output w,x,y,z;
assign w= en & (~a) & (~b);
assign x= en & (~a) & (b);
assign y= en & (a)  & (~b);
assign z= en & (a)  & (b);
endmodule

lab1/decoder_24/decoder_24_tb.v
`timescale 1ns / 1ps
`include "decoder_24.v"

module decoder_24_tb;

    // Testbench signals
    reg a;
    reg b;
    reg en;
    wire w;
    wire x;
    wire y;
    wire z;

    // Instantiate the decoder_24 module
    decoder_24 uut (
        .a(a),
        .b(b),
        .en(en),
        .w(w),
        .x(x),
        .y(y),
        .z(z)
    );

    initial begin
        // Initialize signals
        a = 0;
        b = 0;
        en = 0;

        // Monitor outputs
        $monitor("At time %t: en = %b, a = %b, b = %b -> w = %b, x = %b, y = %b, z = %b", $time, en, a, b, w, x, y, z);

        // Test case 1: Enable = 0, all outputs should be 0
        #10;
        en = 0;
        a = 0;
        b = 0;
        #10;
        en = 0;
        a = 0;
        b = 1;
        #10;
        en = 0;
        a = 1;
        b = 0;
        #10;
        en = 0;
        a = 1;
        b = 1;

        // Test case 2: Enable = 1, check all combinations of a and b
        #10;
        en = 1;
        a = 0;
        b = 0;
        #10;
        en = 1;
        a = 0;
        b = 1;
        #10;
        en = 1;
        a = 1;
        b = 0;
        #10;
        en = 1;
        a = 1;
        b = 1;

        // Finish the simulation
        #10;
        $finish;
    end

   initial begin
        $dumpfile("decoder_24_waveform.vcd");
        $dumpvars(0,decoder_24_tb);
    end
endmodule

lab1/decoder_24/decoder_24_waveform.vcd
$date
	Mon Jul 22 21:46:25 2024
$end
$version
	Icarus Verilog
$end
$timescale
	1ps
$end
$scope module decoder_24_tb $end
$var wire 1 ! z $end
$var wire 1 " y $end
$var wire 1 # x $end
$var wire 1 $ w $end
$var reg 1 % a $end
$var reg 1 & b $end
$var reg 1 ' en $end
$scope module uut $end
$var wire 1 % a $end
$var wire 1 & b $end
$var wire 1 ' en $end
$var wire 1 $ w $end
$var wire 1 # x $end
$var wire 1 " y $end
$var wire 1 ! z $end
$upscope $end
$upscope $end
$enddefinitions $end
#0
$dumpvars
0'
0&
0%
0$
0#
0"
0!
$end
#20000
1&
#30000
0&
1%
#40000
1&
#50000
1$
0&
0%
1'
#60000
0$
1#
1&
#70000
1"
0#
0&
1%
#80000
0"
1!
1&
