lab1/mux_41_decoder _tristatebuffer/mux_41_decoder _tristatebuffer.v
module tristate_buffer(in,sel,out);
input in,sel;
output out;
assign out= sel?in:1'bz;
endmodule

module decoder_24(en,a,b,w,x,y,z);
input a,b,en;
output w,x,y,z;
assign w= en & (~a) & (~b);
assign x= en & (~a) & (b);
assign y= en & (a)  & (~b);
assign z= en & (a)  & (b);
endmodule


module mux_41(en,s0,s1,i0,i1,i2,i3,out);
input en,s0,s1,i0,i1,i2,i3;
output out;
wire m0,m1,m2,m3,W0,W1,W2,W3;

decoder_24 D1(en,s0,s1,m0,m1,m2,m3);
tristate_buffer B1(m0,i0,W0);
tristate_buffer B2(m1,i1,W1);
tristate_buffer B3(m2,i2,W2);
tristate_buffer B4(m3,i3,W3);

assign out= W0 | W1 | W2 | W3;

endmodule

lab1/mux_41_decoder _tristatebuffer/mux_41_decoder _tristatebuffer_tb.v
`timescale 1ns / 1ps
`include "mux_41_decoder _tristatebuffer.v"
module mux_41_tb;

    // Testbench signals
    reg en;
    reg s0;
    reg s1;
    reg i0;
    reg i1;
    reg i2;
    reg i3;
    wire out;

    // Instantiate the mux_41 module
    mux_41 uut (
        .en(en),
        .s0(s0),
        .s1(s1),
        .i0(i0),
        .i1(i1),
        .i2(i2),
        .i3(i3),
        .out(out)
    );

    initial begin
        // Initialize signals
        en = 0;
        s0 = 0;
        s1 = 0;
        i0 = 0;
        i1 = 0;
        i2 = 0;
        i3 = 0;

        // Monitor outputs
        $monitor("At time %t: en = %b, s0 = %b, s1 = %b, i0 = %b, i1 = %b, i2 = %b, i3 = %b -> out = %b", $time, en, s0, s1, i0, i1, i2, i3, out);

        // Test case: Enable = 0, all inputs and select lines = 0
        #10;
        en = 0; s0 = 0; s1 = 0; i0 = 0; i1 = 0; i2 = 0; i3 = 0;
        
        // Test all combinations of inputs and select lines with enable = 1
        #10; en = 1; s0 = 0; s1 = 0; i0 = 1; i1 = 0; i2 = 0; i3 = 0;
        #10; en = 1; s0 = 0; s1 = 1; i0 = 0; i1 = 1; i2 = 0; i3 = 0;
        #10; en = 1; s0 = 1; s1 = 0; i0 = 0; i1 = 0; i2 = 1; i3 = 0;
        #10; en = 1; s0 = 1; s1 = 1; i0 = 0; i1 = 0; i2 = 0; i3 = 1;

        // Test with different data inputs and select lines
        #10; en = 1; s0 = 0; s1 = 0; i0 = 1; i1 = 1; i2 = 1; i3 = 1;
        #10; en = 1; s0 = 0; s1 = 1; i0 = 1; i1 = 1; i2 = 1; i3 = 1;
        #10; en = 1; s0 = 1; s1 = 0; i0 = 1; i1 = 1; i2 = 1; i3 = 1;
        #10; en = 1; s0 = 1; s1 = 1; i0 = 1; i1 = 1; i2 = 1; i3 = 1;

        // Test with enable = 0
        #10; en = 0; s0 = 0; s1 = 0; i0 = 1; i1 = 0; i2 = 0; i3 = 0;
        #10; en = 0; s0 = 0; s1 = 1; i0 = 0; i1 = 1; i2 = 0; i3 = 0;
        #10; en = 0; s0 = 1; s1 = 0; i0 = 0; i1 = 0; i2 = 1; i3 = 0;
        #10; en = 0; s0 = 1; s1 = 1; i0 = 0; i1 = 0; i2 = 0; i3 = 1;

        // Finish the simulation
        #10;
        $finish;
    end
           initial begin
        $dumpfile("mux_41_tb_waveform.vcd");
        $dumpvars(0,mux_41_tb);
    end


endmodule

lab1/mux_41_decoder _tristatebuffer/mux_41_tb_waveform.vcd
$date
	Mon Jul 22 22:59:56 2024
$end
$version
	Icarus Verilog
$end
$timescale
	1ps
$end
$scope module mux_41_tb $end
$var wire 1 ! out $end
$var reg 1 " en $end
$var reg 1 # i0 $end
$var reg 1 $ i1 $end
$var reg 1 % i2 $end
$var reg 1 & i3 $end
$var reg 1 ' s0 $end
$var reg 1 ( s1 $end
$scope module uut $end
$var wire 1 " en $end
$var wire 1 # i0 $end
$var wire 1 $ i1 $end
$var wire 1 % i2 $end
$var wire 1 & i3 $end
$var wire 1 ! out $end
$var wire 1 ' s0 $end
$var wire 1 ( s1 $end
$var wire 1 ) m3 $end
$var wire 1 * m2 $end
$var wire 1 + m1 $end
$var wire 1 , m0 $end
$var wire 1 - W3 $end
$var wire 1 . W2 $end
$var wire 1 / W1 $end
$var wire 1 0 W0 $end
$scope module B1 $end
$var wire 1 # sel $end
$var wire 1 0 out $end
$var wire 1 , in $end
$upscope $end
$scope module B2 $end
$var wire 1 $ sel $end
$var wire 1 / out $end
$var wire 1 + in $end
$upscope $end
$scope module B3 $end
$var wire 1 % sel $end
$var wire 1 . out $end
$var wire 1 * in $end
$upscope $end
$scope module B4 $end
$var wire 1 & sel $end
$var wire 1 - out $end
$var wire 1 ) in $end
$upscope $end
$scope module D1 $end
$var wire 1 ' a $end
$var wire 1 ( b $end
$var wire 1 " en $end
$var wire 1 , w $end
$var wire 1 + x $end
$var wire 1 * y $end
$var wire 1 ) z $end
$upscope $end
$upscope $end
$upscope $end
$enddefinitions $end
#0
$dumpvars
z0
z/
z.
z-
0,
0+
0*
0)
0(
0'
0&
0%
0$
0#
0"
x!
$end
#20000
1!
1,
10
1#
1"
#30000
0,
1/
z0
1+
1$
0#
1(
#40000
1!
1*
1.
z/
0+
1%
0$
0(
1'
#50000
0*
1-
z.
1)
1&
0%
1(
#60000
1!
1,
0-
0.
0/
10
0)
1%
1$
1#
0(
0'
#70000
00
0,
1/
1+
1(
#80000
1.
0/
1*
0+
0(
1'
#90000
0.
0*
1-
1)
1(
#100000
x!
z-
z.
z/
0)
0&
0%
0$
0(
0'
0"
#110000
0/
z0
1$
0#
1(
#120000
0.
z/
1%
0$
0(
1'
#130000
0-
z.
1&
0%
1(
